{"State.e85f148d-9855-4e00-a124-f467fdaa72b7": {"created_at": "2025-01-02T04:04:41.012980", "updated_at": "2025-01-02T04:04:41.013070", "id": "e85f148d-9855-4e00-a124-f467fdaa72b7", "name": "California", "__class__": "State"}, "State.a6406aed-158e-4bdf-a028-a147a3aec291": {"created_at": "2025-01-02T04:04:41.013398", "updated_at": "2025-01-02T04:04:41.013448", "id": "a6406aed-158e-4bdf-a028-a147a3aec291", "name": "Arizona", "__class__": "State"}, "Place.4920d34a-4102-4b2d-9223-98bb600fef5c": {"created_at": "2025-01-02T04:04:41.013862", "updated_at": "2025-01-02T04:04:41.013940", "id": "4920d34a-4102-4b2d-9223-98bb600fef5c", "city_id": "0001", "user_id": "0001", "name": "My little house", "number_rooms": 4, "number_bathrooms": 2, "max_guest": 10, "price_by_night": 300, "latitude": 37.773972, "longitude": -122.431297, "__class__": "Place"}, "State.2b9733bb-298d-47d2-9084-7d80634a369b": {"id": "2b9733bb-298d-47d2-9084-7d80634a369b", "created_at": "2025-01-02T04:04:45.968232", "updated_at": "2025-01-02T04:04:45.968307", "name": "California", "__class__": "State"}, "State.9a0afa9c-b6e2-4bfb-aba9-dba08d1de0da": {"id": "9a0afa9c-b6e2-4bfb-aba9-dba08d1de0da", "created_at": "2025-01-02T04:04:45.968758", "updated_at": "2025-01-02T04:04:45.968814", "name": "Arizona", "__class__": "State"}, "Place.50168ec1-1324-4fa4-8938-33dc8bcb3324": {"id": "50168ec1-1324-4fa4-8938-33dc8bcb3324", "created_at": "2025-01-02T04:04:45.978073", "updated_at": "2025-01-02T04:04:45.978190", "city_id": "0001", "user_id": "0001", "name": "My little house", "number_rooms": 4, "number_bathrooms": 2, "max_guest": 10, "price_by_night": 300, "latitude": 37.773972, "longitude": -122.431297, "__class__": "Place"}}